mps_youtube/__init__.py
mps_youtube/c.py
mps_youtube/cache.py
mps_youtube/config.py
mps_youtube/content.py
mps_youtube/contentquery.py
mps_youtube/description_parser.py
mps_youtube/g.py
mps_youtube/helptext.py
mps_youtube/history.py
mps_youtube/init.py
mps_youtube/main.py
mps_youtube/mpris.py
mps_youtube/pafy.py
mps_youtube/paths.py
mps_youtube/player.py
mps_youtube/playlist.py
mps_youtube/playlists.py
mps_youtube/screen.py
mps_youtube/streams.py
mps_youtube/terminalsize.py
mps_youtube/util.py
mps_youtube/commands/__init__.py
mps_youtube/commands/album_search.py
mps_youtube/commands/config.py
mps_youtube/commands/download.py
mps_youtube/commands/generate_playlist.py
mps_youtube/commands/lastfm.py
mps_youtube/commands/local_playlist.py
mps_youtube/commands/misc.py
mps_youtube/commands/play.py
mps_youtube/commands/search.py
mps_youtube/commands/songlist.py
mps_youtube/commands/spotify_playlist.py
mps_youtube/listview/__init__.py
mps_youtube/listview/base.py
mps_youtube/listview/livestream.py
mps_youtube/listview/songtitle.py
mps_youtube/listview/user.py
mps_youtube/players/GenericPlayer.py
mps_youtube/players/__init__.py
mps_youtube/players/mplayer.py
mps_youtube/players/mpv.py
mps_youtube/players/vlc.py
yewtube-2.12.0.data/data/share/applications/yewtube.desktop
yewtube-2.12.0.dist-info/LICENSE
yewtube-2.12.0.dist-info/METADATA
yewtube-2.12.0.dist-info/WHEEL
yewtube-2.12.0.dist-info/entry_points.txt
yewtube-2.12.0.dist-info/top_level.txt
yewtube-2.12.0.dist-info/RECORD
