Metadata-Version: 2.1
Name: yewtube
Version: 2.12.0
Summary: A Terminal based YouTube player and downloader. No Youtube API key required. Forked from mps-youtube
Home-page: https://github.com/mps-youtube/yewtube
Download-URL: https://github.com/mps-youtube/yewtube/releases
Author: talha_programmer
Author-email: iamtalhaasghar@gmail.com
Keywords: video,music,audio,youtube,stream,download
Classifier: Topic :: Utilities
Classifier: Topic :: Internet :: WWW/HTTP
Classifier: Topic :: Multimedia :: Sound/Audio :: Players
Classifier: Topic :: Multimedia :: Video
Classifier: Environment :: Console
Classifier: Environment :: Win32 (MS Windows)
Classifier: Environment :: MacOS X
Classifier: Operating System :: POSIX :: Linux
Classifier: Operating System :: MacOS
Classifier: Operating System :: MacOS :: MacOS 9
Classifier: Operating System :: MacOS :: MacOS X
Classifier: Operating System :: Microsoft
Classifier: Operating System :: Microsoft :: Windows :: Windows 7
Classifier: Operating System :: Microsoft :: Windows :: Windows XP
Classifier: Operating System :: Microsoft :: Windows :: Windows Vista
Classifier: Intended Audience :: End Users/Desktop
Classifier: Programming Language :: Python
Classifier: Programming Language :: Python :: 3
Classifier: Programming Language :: Python :: 3.3
Classifier: Programming Language :: Python :: 3.4
Classifier: Programming Language :: Python :: 3 :: Only
Classifier: Development Status :: 5 - Production/Stable
Classifier: License :: OSI Approved :: GNU General Public License v3 (GPLv3)
Requires-Python: >=3.6
License-File: LICENSE
Requires-Dist: requests
Requires-Dist: pyperclip
Requires-Dist: youtube-search-python >=1.6.5
Requires-Dist: yt-dlp >=2023.7.6
Requires-Dist: pylast
Requires-Dist: pyreadline3 ; platform_system == "Windows"
Requires-Dist: colorama ; platform_system == "Windows"
Provides-Extra: docs
Requires-Dist: mkdocs-gen-files >=0.3.4 ; extra == 'docs'
Requires-Dist: mkdocs-literate-nav >=0.4.1 ; extra == 'docs'
Requires-Dist: mkdocs-macros-plugin >=0.6.4 ; extra == 'docs'
Requires-Dist: mkdocs-material >=8.2.1 ; extra == 'docs'
Requires-Dist: mkdocstrings-python-legacy >=0.2.2 ; extra == 'docs'
Requires-Dist: mkdocstrings >=0.18.0 ; extra == 'docs'
Provides-Extra: mpris
Requires-Dist: dbus-python >=1.2.18 ; extra == 'mpris'
Requires-Dist: PyGObject >=3.42.0 ; extra == 'mpris'
